{
  "best_global_step": null,
  "best_metric": null,
  "best_model_checkpoint": null,
  "epoch": 0.026716537536735238,
  "eval_steps": 100.0,
  "global_step": 200,
  "is_hyper_param_search": false,
  "is_local_process_zero": true,
  "is_world_process_zero": true,
  "log_history": [
    {
      "clip_ratio/high_max": 0.0,
      "clip_ratio/high_mean": 0.0,
      "clip_ratio/low_mean": 0.0,
      "clip_ratio/low_min": 0.0,
      "clip_ratio/region_mean": 0.0,
      "completions/clipped_ratio": 0.0,
      "completions/max_length": 475.0,
      "completions/mean_length": 217.9375,
      "completions/min_length": 98.0,
      "epoch": 0.0001335826876836762,
      "frac_reward_zero_std": 0.5,
      "grad_norm": 0.11047431081533432,
      "kl": 0.0,
      "learning_rate": 6.666666666666667e-06,
      "loss": -0.03265845403075218,
      "reward": 0.4413774609565735,
      "reward_std": 0.1784307360649109,
      "rewards/GRPOAccuracyReward/mean": 0.4413774609565735,
      "rewards/GRPOAccuracyReward/std": 0.5169445872306824,
      "step": 1
    },
    {
      "clip_ratio/high_max": 2.3225566514560745e-05,
      "clip_ratio/high_mean": 2.3225566514560745e-05,
      "clip_ratio/low_mean": 0.0,
      "clip_ratio/low_min": 0.0,
      "clip_ratio/region_mean": 2.3225566514560745e-05,
      "completions/clipped_ratio": 0.20833333333333334,
      "completions/max_length": 483.1111111111111,
      "completions/mean_length": 249.04861111111111,
      "completions/min_length": 99.0,
      "epoch": 0.0013358268768367619,
      "frac_reward_zero_std": 0.6666666666666666,
      "grad_norm": 0.001204076106660068,
      "kl": 0.0002806790588591765,
      "learning_rate": 6.666666666666667e-05,
      "loss": -0.0005718615009552903,
      "reward": 0.0629642903804779,
      "reward_std": 0.13707024355729422,
      "rewards/GRPOAccuracyReward/mean": 0.0629642903804779,
      "rewards/GRPOAccuracyReward/std": 0.18093351854218376,
      "step": 10
    },
    {
      "clip_ratio/high_max": 5.1040326070506126e-05,
      "clip_ratio/high_mean": 5.1040326070506126e-05,
      "clip_ratio/low_mean": 2.4248303088825195e-05,
      "clip_ratio/low_min": 2.4248303088825195e-05,
      "clip_ratio/region_mean": 7.528862915933132e-05,
      "completions/clipped_ratio": 0.31875,
      "completions/max_length": 512.0,
      "completions/mean_length": 295.4625,
      "completions/min_length": 119.4,
      "epoch": 0.0026716537536735237,
      "frac_reward_zero_std": 0.75,
      "grad_norm": 0.08089763671159744,
      "kl": 0.0015113644782104529,
      "learning_rate": 9.992407582166581e-05,
      "loss": -0.004504628479480743,
      "reward": 0.15717957466840743,
      "reward_std": 0.09719549119472504,
      "rewards/GRPOAccuracyReward/mean": 0.15717957466840743,
      "rewards/GRPOAccuracyReward/std": 0.1514858990907669,
      "step": 20
    },
    {
      "clip_ratio/high_max": 0.00011334241135045886,
      "clip_ratio/high_mean": 0.00011334241135045886,
      "clip_ratio/low_mean": 6.996922747930512e-05,
      "clip_ratio/low_min": 6.996922747930512e-05,
      "clip_ratio/region_mean": 0.00018331163882976398,
      "completions/clipped_ratio": 0.29375,
      "completions/max_length": 480.3,
      "completions/mean_length": 288.05,
      "completions/min_length": 102.2,
      "epoch": 0.004007480630510286,
      "frac_reward_zero_std": 0.3,
      "grad_norm": 0.15130865573883057,
      "kl": 0.0226828177284915,
      "learning_rate": 9.931806517013612e-05,
      "loss": -0.02843758761882782,
      "reward": 0.3608807295560837,
      "reward_std": 0.33002361804246905,
      "rewards/GRPOAccuracyReward/mean": 0.3608807295560837,
      "rewards/GRPOAccuracyReward/std": 0.4457370311021805,
      "step": 30
    },
    {
      "clip_ratio/high_max": 0.00031060790497576817,
      "clip_ratio/high_mean": 0.00031060790497576817,
      "clip_ratio/low_mean": 1.5713387983851135e-05,
      "clip_ratio/low_min": 1.5713387983851135e-05,
      "clip_ratio/region_mean": 0.0003263212929596193,
      "completions/clipped_ratio": 0.7375,
      "completions/max_length": 512.0,
      "completions/mean_length": 439.44375,
      "completions/min_length": 210.7,
      "epoch": 0.0053433075073470475,
      "frac_reward_zero_std": 0.25,
      "grad_norm": 0.08629006892442703,
      "kl": 0.04127161803189665,
      "learning_rate": 9.811340001546251e-05,
      "loss": -0.023407900333404542,
      "reward": 0.6014016658067703,
      "reward_std": 0.2629090167582035,
      "rewards/GRPOAccuracyReward/mean": 0.6014016658067703,
      "rewards/GRPOAccuracyReward/std": 0.37672483921051025,
      "step": 40
    },
    {
      "clip_ratio/high_max": 0.00021898309350945055,
      "clip_ratio/high_mean": 0.00021898309350945055,
      "clip_ratio/low_mean": 6.350035982904956e-05,
      "clip_ratio/low_min": 6.350035982904956e-05,
      "clip_ratio/region_mean": 0.00028248345333850013,
      "completions/clipped_ratio": 0.9125,
      "completions/max_length": 512.0,
      "completions/mean_length": 487.65,
      "completions/min_length": 279.8,
      "epoch": 0.0066791343841838095,
      "frac_reward_zero_std": 0.1,
      "grad_norm": 0.004237829707562923,
      "kl": 0.04604808324947953,
      "learning_rate": 9.632470336074009e-05,
      "loss": -0.02242465168237686,
      "reward": 0.6004299104213715,
      "reward_std": 0.4992217391729355,
      "rewards/GRPOAccuracyReward/mean": 0.6004299104213715,
      "rewards/GRPOAccuracyReward/std": 0.57076096534729,
      "step": 50
    },
    {
      "clip_ratio/high_max": 0.00018880088755395262,
      "clip_ratio/high_mean": 0.00018880088755395262,
      "clip_ratio/low_mean": 4.8828125e-05,
      "clip_ratio/low_min": 4.8828125e-05,
      "clip_ratio/region_mean": 0.00023762901255395264,
      "completions/clipped_ratio": 0.96875,
      "completions/max_length": 512.0,
      "completions/mean_length": 502.45625,
      "completions/min_length": 360.3,
      "epoch": 0.008014961261020572,
      "frac_reward_zero_std": 0.1,
      "grad_norm": 0.0417831689119339,
      "kl": 0.0419632310513407,
      "learning_rate": 9.397368756032445e-05,
      "loss": -0.006319853663444519,
      "reward": 0.8362790673971177,
      "reward_std": 0.40335172712802886,
      "rewards/GRPOAccuracyReward/mean": 0.8362790673971177,
      "rewards/GRPOAccuracyReward/std": 0.6048758268356323,
      "step": 60
    },
    {
      "clip_ratio/high_max": 5.1026164146605876e-05,
      "clip_ratio/high_mean": 5.1026164146605876e-05,
      "clip_ratio/low_mean": 3.662109375e-05,
      "clip_ratio/low_min": 3.662109375e-05,
      "clip_ratio/region_mean": 8.764725789660588e-05,
      "completions/clipped_ratio": 0.98125,
      "completions/max_length": 512.0,
      "completions/mean_length": 506.3,
      "completions/min_length": 451.0,
      "epoch": 0.009350788137857334,
      "frac_reward_zero_std": 0.15,
      "grad_norm": 0.045524172484874725,
      "kl": 0.03815256403759122,
      "learning_rate": 9.108889076126226e-05,
      "loss": 0.0025570368394255637,
      "reward": 0.7456768453121185,
      "reward_std": 0.3445108599960804,
      "rewards/GRPOAccuracyReward/mean": 0.7456768453121185,
      "rewards/GRPOAccuracyReward/std": 0.5920978963375092,
      "step": 70
    },
    {
      "clip_ratio/high_max": 2.753035369096324e-05,
      "clip_ratio/high_mean": 2.753035369096324e-05,
      "clip_ratio/low_mean": 3.9255988667719066e-05,
      "clip_ratio/low_min": 3.9255988667719066e-05,
      "clip_ratio/region_mean": 6.67863423586823e-05,
      "completions/clipped_ratio": 0.9625,
      "completions/max_length": 512.0,
      "completions/mean_length": 497.9,
      "completions/min_length": 327.6,
      "epoch": 0.010686615014694095,
      "frac_reward_zero_std": 0.3,
      "grad_norm": 0.03637024015188217,
      "kl": 0.045922115165740254,
      "learning_rate": 8.770533048884482e-05,
      "loss": -0.006419476121664047,
      "reward": 0.6162907242774963,
      "reward_std": 0.2593272943049669,
      "rewards/GRPOAccuracyReward/mean": 0.6162907242774963,
      "rewards/GRPOAccuracyReward/std": 0.5702457137405872,
      "step": 80
    },
    {
      "clip_ratio/high_max": 9.274109761463478e-05,
      "clip_ratio/high_mean": 9.274109761463478e-05,
      "clip_ratio/low_mean": 2.44140625e-05,
      "clip_ratio/low_min": 2.44140625e-05,
      "clip_ratio/region_mean": 0.00011715516011463478,
      "completions/clipped_ratio": 0.9375,
      "completions/max_length": 512.0,
      "completions/mean_length": 490.925,
      "completions/min_length": 288.3,
      "epoch": 0.012022441891530858,
      "frac_reward_zero_std": 0.3,
      "grad_norm": 0.07036864012479782,
      "kl": 0.05020056050270796,
      "learning_rate": 8.386407858128706e-05,
      "loss": -0.017026934027671813,
      "reward": 0.5782822467386722,
      "reward_std": 0.3232184508815408,
      "rewards/GRPOAccuracyReward/mean": 0.5782822467386722,
      "rewards/GRPOAccuracyReward/std": 0.5626206874847413,
      "step": 90
    },
    {
      "clip_ratio/high_max": 1.220703125e-05,
      "clip_ratio/high_mean": 1.220703125e-05,
      "clip_ratio/low_mean": 1.220703125e-05,
      "clip_ratio/low_min": 1.220703125e-05,
      "clip_ratio/region_mean": 2.44140625e-05,
      "completions/clipped_ratio": 0.95,
      "completions/max_length": 512.0,
      "completions/mean_length": 498.99375,
      "completions/min_length": 355.3,
      "epoch": 0.013358268768367619,
      "frac_reward_zero_std": 0.55,
      "grad_norm": 0.18384228646755219,
      "kl": 0.49792842399328946,
      "learning_rate": 7.961176263324901e-05,
      "loss": 0.007514745742082596,
      "reward": 0.20203981399536133,
      "reward_std": 0.2594357207417488,
      "rewards/GRPOAccuracyReward/mean": 0.20203981399536133,
      "rewards/GRPOAccuracyReward/std": 0.3216036558151245,
      "step": 100
    },
    {
      "clip_ratio/high_max": 1.220703125e-05,
      "clip_ratio/high_mean": 1.220703125e-05,
      "clip_ratio/low_mean": 1.4841198571957648e-05,
      "clip_ratio/low_min": 1.4841198571957648e-05,
      "clip_ratio/region_mean": 2.7048229821957647e-05,
      "completions/clipped_ratio": 0.98125,
      "completions/max_length": 512.0,
      "completions/mean_length": 504.86875,
      "completions/min_length": 433.8,
      "epoch": 0.014694095645204382,
      "frac_reward_zero_std": 0.5,
      "grad_norm": 0.9197866320610046,
      "kl": 1.321320040524006,
      "learning_rate": 7.500000000000001e-05,
      "loss": 0.02537115812301636,
      "reward": 0.2143993966281414,
      "reward_std": 0.3141354665160179,
      "rewards/GRPOAccuracyReward/mean": 0.2143993966281414,
      "rewards/GRPOAccuracyReward/std": 0.3851689338684082,
      "step": 110
    },
    {
      "clip_ratio/high_max": 5.187904462218284e-05,
      "clip_ratio/high_mean": 5.187904462218284e-05,
      "clip_ratio/low_mean": 1.354646374238655e-05,
      "clip_ratio/low_min": 1.354646374238655e-05,
      "clip_ratio/region_mean": 6.54255083645694e-05,
      "completions/clipped_ratio": 0.94375,
      "completions/max_length": 512.0,
      "completions/mean_length": 494.1625,
      "completions/min_length": 251.9,
      "epoch": 0.016029922522041145,
      "frac_reward_zero_std": 0.55,
      "grad_norm": 0.46585187315940857,
      "kl": 1.7864469900727271,
      "learning_rate": 7.008477123264848e-05,
      "loss": 0.028751516342163087,
      "reward": 0.29008724093437194,
      "reward_std": 0.2770570322871208,
      "rewards/GRPOAccuracyReward/mean": 0.29008724093437194,
      "rewards/GRPOAccuracyReward/std": 0.4651067018508911,
      "step": 120
    },
    {
      "clip_ratio/high_max": 1.3119916548021138e-05,
      "clip_ratio/high_mean": 1.3119916548021138e-05,
      "clip_ratio/low_mean": 1.220703125e-05,
      "clip_ratio/low_min": 1.220703125e-05,
      "clip_ratio/region_mean": 2.532694779802114e-05,
      "completions/clipped_ratio": 0.91875,
      "completions/max_length": 512.0,
      "completions/mean_length": 486.64375,
      "completions/min_length": 273.6,
      "epoch": 0.017365749398877906,
      "frac_reward_zero_std": 0.25,
      "grad_norm": 1.061325192451477,
      "kl": 1.2538649942725897,
      "learning_rate": 6.492574055008473e-05,
      "loss": 0.013638255000114442,
      "reward": 0.36895922422409055,
      "reward_std": 0.4289454370737076,
      "rewards/GRPOAccuracyReward/mean": 0.36895922422409055,
      "rewards/GRPOAccuracyReward/std": 0.5068929135799408,
      "step": 130
    },
    {
      "clip_ratio/high_max": 1.3390465755946935e-05,
      "clip_ratio/high_mean": 1.3390465755946935e-05,
      "clip_ratio/low_mean": 3.9124931208789346e-05,
      "clip_ratio/low_min": 3.9124931208789346e-05,
      "clip_ratio/region_mean": 5.2515396964736284e-05,
      "completions/clipped_ratio": 0.89375,
      "completions/max_length": 512.0,
      "completions/mean_length": 479.2375,
      "completions/min_length": 213.0,
      "epoch": 0.018701576275714667,
      "frac_reward_zero_std": 0.4,
      "grad_norm": 0.5345914363861084,
      "kl": 1.9983285177499055,
      "learning_rate": 5.958553159618693e-05,
      "loss": 0.022902040183544158,
      "reward": 0.27311566546559335,
      "reward_std": 0.3614194691181183,
      "rewards/GRPOAccuracyReward/mean": 0.27311566546559335,
      "rewards/GRPOAccuracyReward/std": 0.44732911586761476,
      "step": 140
    },
    {
      "clip_ratio/high_max": 1.220703125e-05,
      "clip_ratio/high_mean": 1.220703125e-05,
      "clip_ratio/low_mean": 3.727414441527799e-05,
      "clip_ratio/low_min": 3.727414441527799e-05,
      "clip_ratio/region_mean": 4.948117566527799e-05,
      "completions/clipped_ratio": 0.8375,
      "completions/max_length": 512.0,
      "completions/mean_length": 461.2125,
      "completions/min_length": 157.6,
      "epoch": 0.02003740315255143,
      "frac_reward_zero_std": 0.5,
      "grad_norm": 0.0545407235622406,
      "kl": 1.851288946904242,
      "learning_rate": 5.4128967273616625e-05,
      "loss": 0.000176599295809865,
      "reward": 0.37336633279919623,
      "reward_std": 0.20914659798145294,
      "rewards/GRPOAccuracyReward/mean": 0.37336633279919623,
      "rewards/GRPOAccuracyReward/std": 0.37426992058753966,
      "step": 150
    },
    {
      "clip_ratio/high_max": 7.976260967552662e-05,
      "clip_ratio/high_mean": 7.976260967552662e-05,
      "clip_ratio/low_mean": 2.5160399673040956e-05,
      "clip_ratio/low_min": 2.5160399673040956e-05,
      "clip_ratio/region_mean": 0.00010492300934856757,
      "completions/clipped_ratio": 0.89375,
      "completions/max_length": 512.0,
      "completions/mean_length": 472.23125,
      "completions/min_length": 208.9,
      "epoch": 0.02137323002938819,
      "frac_reward_zero_std": 0.35,
      "grad_norm": 0.0680975615978241,
      "kl": 0.4194012232124805,
      "learning_rate": 4.8622282881591906e-05,
      "loss": -0.023718041181564332,
      "reward": 0.5152132138609886,
      "reward_std": 0.35381869077682493,
      "rewards/GRPOAccuracyReward/mean": 0.5152132138609886,
      "rewards/GRPOAccuracyReward/std": 0.5423572599887848,
      "step": 160
    },
    {
      "clip_ratio/high_max": 5.5874795361887666e-05,
      "clip_ratio/high_mean": 5.5874795361887666e-05,
      "clip_ratio/low_mean": 1.3631406181957572e-05,
      "clip_ratio/low_min": 1.3631406181957572e-05,
      "clip_ratio/region_mean": 6.950620154384523e-05,
      "completions/clipped_ratio": 0.86875,
      "completions/max_length": 512.0,
      "completions/mean_length": 468.8125,
      "completions/min_length": 221.6,
      "epoch": 0.022709056906224954,
      "frac_reward_zero_std": 0.35,
      "grad_norm": 0.10576824098825455,
      "kl": 1.90394737906754,
      "learning_rate": 4.3132322109079596e-05,
      "loss": 0.01292601227760315,
      "reward": 0.40414938479661944,
      "reward_std": 0.40166368782520295,
      "rewards/GRPOAccuracyReward/mean": 0.40414938479661944,
      "rewards/GRPOAccuracyReward/std": 0.573333665728569,
      "step": 170
    },
    {
      "clip_ratio/high_max": 2.44140625e-05,
      "clip_ratio/high_mean": 2.44140625e-05,
      "clip_ratio/low_mean": 1.3430029503069818e-05,
      "clip_ratio/low_min": 1.3430029503069818e-05,
      "clip_ratio/region_mean": 3.784409200306982e-05,
      "completions/clipped_ratio": 0.9375,
      "completions/max_length": 512.0,
      "completions/mean_length": 494.275,
      "completions/min_length": 282.9,
      "epoch": 0.024044883783061716,
      "frac_reward_zero_std": 0.4,
      "grad_norm": 0.30463072657585144,
      "kl": 2.136623853072524,
      "learning_rate": 3.772572564296005e-05,
      "loss": 0.036876913905143735,
      "reward": 0.341534461081028,
      "reward_std": 0.35016459226608276,
      "rewards/GRPOAccuracyReward/mean": 0.341534461081028,
      "rewards/GRPOAccuracyReward/std": 0.4929429769515991,
      "step": 180
    },
    {
      "clip_ratio/high_max": 3.662109375e-05,
      "clip_ratio/high_mean": 3.662109375e-05,
      "clip_ratio/low_mean": 4.8828125e-05,
      "clip_ratio/low_min": 4.8828125e-05,
      "clip_ratio/region_mean": 8.544921875e-05,
      "completions/clipped_ratio": 0.9625,
      "completions/max_length": 512.0,
      "completions/mean_length": 498.5625,
      "completions/min_length": 319.7,
      "epoch": 0.025380710659898477,
      "frac_reward_zero_std": 0.35,
      "grad_norm": 0.4535386562347412,
      "kl": 2.864472159743309,
      "learning_rate": 3.2468122240362284e-05,
      "loss": 0.057679831981658936,
      "reward": 0.3963357463479042,
      "reward_std": 0.34131393283605577,
      "rewards/GRPOAccuracyReward/mean": 0.3963357463479042,
      "rewards/GRPOAccuracyReward/std": 0.5351481437683105,
      "step": 190
    },
    {
      "clip_ratio/high_max": 1.3498919724952429e-05,
      "clip_ratio/high_mean": 1.3498919724952429e-05,
      "clip_ratio/low_mean": 0.0,
      "clip_ratio/low_min": 0.0,
      "clip_ratio/region_mean": 1.3498919724952429e-05,
      "completions/clipped_ratio": 0.93125,
      "completions/max_length": 512.0,
      "completions/mean_length": 487.7125,
      "completions/min_length": 210.3,
      "epoch": 0.026716537536735238,
      "frac_reward_zero_std": 0.45,
      "grad_norm": 0.24195221066474915,
      "kl": 3.1328652083873747,
      "learning_rate": 2.7423332084455544e-05,
      "loss": 0.05745983123779297,
      "reward": 0.24991650581359864,
      "reward_std": 0.30923409312963485,
      "rewards/GRPOAccuracyReward/mean": 0.24991650581359864,
      "rewards/GRPOAccuracyReward/std": 0.44812862277030946,
      "step": 200
    }
  ],
  "logging_steps": 10,
  "max_steps": 300,
  "num_input_tokens_seen": 0,
  "num_train_epochs": 1,
  "save_steps": 100,
  "stateful_callbacks": {
    "TrainerControl": {
      "args": {
        "should_epoch_stop": false,
        "should_evaluate": false,
        "should_log": false,
        "should_save": true,
        "should_training_stop": false
      },
      "attributes": {}
    }
  },
  "total_flos": 0.0,
  "train_batch_size": 8,
  "trial_name": null,
  "trial_params": null
}
