{
  "best_global_step": null,
  "best_metric": null,
  "best_model_checkpoint": null,
  "epoch": 0.06435006435006435,
  "eval_steps": 100.0,
  "global_step": 300,
  "is_hyper_param_search": false,
  "is_local_process_zero": true,
  "is_world_process_zero": true,
  "log_history": [
    {
      "clip_ratio/high_max": 0.0,
      "clip_ratio/high_mean": 0.0,
      "clip_ratio/low_mean": 0.0,
      "clip_ratio/low_min": 0.0,
      "clip_ratio/region_mean": 0.0,
      "completions/clipped_ratio": 0.0,
      "completions/max_length": 158.0,
      "completions/mean_length": 123.1875,
      "completions/min_length": 82.0,
      "epoch": 0.0002145002145002145,
      "frac_reward_zero_std": 0.0,
      "grad_norm": 0.1367359161376953,
      "kl": 0.0,
      "learning_rate": 6.666666666666667e-06,
      "loss": -0.006050387397408485,
      "reward": 0.694116473197937,
      "reward_std": 0.49462252855300903,
      "rewards/GRPOAccuracyReward/mean": 0.694116473197937,
      "rewards/GRPOAccuracyReward/std": 0.4833926558494568,
      "step": 1
    },
    {
      "clip_ratio/high_max": 0.0002311177086085081,
      "clip_ratio/high_mean": 0.0002311177086085081,
      "clip_ratio/low_mean": 7.89141437659661e-05,
      "clip_ratio/low_min": 7.89141437659661e-05,
      "clip_ratio/region_mean": 0.0003100318523744742,
      "completions/clipped_ratio": 0.006944444444444444,
      "completions/max_length": 222.33333333333334,
      "completions/mean_length": 90.01388888888889,
      "completions/min_length": 27.11111111111111,
      "epoch": 0.002145002145002145,
      "frac_reward_zero_std": 0.3333333333333333,
      "grad_norm": 0.15342745184898376,
      "kl": 0.0023376134611478644,
      "learning_rate": 6.666666666666667e-05,
      "loss": 0.005706165399816301,
      "reward": 0.735683368311988,
      "reward_std": 0.21449058746091193,
      "rewards/GRPOAccuracyReward/mean": 0.735683368311988,
      "rewards/GRPOAccuracyReward/std": 0.3932459813853105,
      "step": 10
    },
    {
      "clip_ratio/high_max": 0.00022887534287292511,
      "clip_ratio/high_mean": 0.00022887534287292511,
      "clip_ratio/low_mean": 0.00020678688306361437,
      "clip_ratio/low_min": 0.00020678688306361437,
      "clip_ratio/region_mean": 0.00043566222593653946,
      "completions/clipped_ratio": 0.0,
      "completions/max_length": 246.3,
      "completions/mean_length": 128.78125,
      "completions/min_length": 68.4,
      "epoch": 0.00429000429000429,
      "frac_reward_zero_std": 0.1,
      "grad_norm": 0.06213536113500595,
      "kl": 0.01678187704528682,
      "learning_rate": 9.992407582166581e-05,
      "loss": -0.02309282124042511,
      "reward": 0.8326867878437042,
      "reward_std": 0.10421294961124658,
      "rewards/GRPOAccuracyReward/mean": 0.8326867878437042,
      "rewards/GRPOAccuracyReward/std": 0.22021203842014075,
      "step": 20
    },
    {
      "clip_ratio/high_max": 0.00020454989571589978,
      "clip_ratio/high_mean": 0.00020454989571589978,
      "clip_ratio/low_mean": 0.0,
      "clip_ratio/low_min": 0.0,
      "clip_ratio/region_mean": 0.00020454989571589978,
      "completions/clipped_ratio": 0.03125,
      "completions/max_length": 321.8,
      "completions/mean_length": 197.73125,
      "completions/min_length": 120.0,
      "epoch": 0.006435006435006435,
      "frac_reward_zero_std": 0.1,
      "grad_norm": 0.12466806173324585,
      "kl": 0.03924171659164131,
      "learning_rate": 9.931806517013612e-05,
      "loss": -0.0015474921092391014,
      "reward": 0.818280690908432,
      "reward_std": 0.23052481431514024,
      "rewards/GRPOAccuracyReward/mean": 0.818280690908432,
      "rewards/GRPOAccuracyReward/std": 0.3478857707232237,
      "step": 30
    },
    {
      "clip_ratio/high_max": 0.00014299105387181044,
      "clip_ratio/high_mean": 0.00014299105387181044,
      "clip_ratio/low_mean": 4.042037180624902e-05,
      "clip_ratio/low_min": 4.042037180624902e-05,
      "clip_ratio/region_mean": 0.00018341142567805945,
      "completions/clipped_ratio": 0.0,
      "completions/max_length": 289.9,
      "completions/mean_length": 174.15,
      "completions/min_length": 95.7,
      "epoch": 0.00858000858000858,
      "frac_reward_zero_std": 0.15,
      "grad_norm": 0.1259298026561737,
      "kl": 0.051977366860955956,
      "learning_rate": 9.811340001546251e-05,
      "loss": -0.028041347861289978,
      "reward": 0.8205552995204926,
      "reward_std": 0.13916075816377999,
      "rewards/GRPOAccuracyReward/mean": 0.8205552995204926,
      "rewards/GRPOAccuracyReward/std": 0.2979220228269696,
      "step": 40
    },
    {
      "clip_ratio/high_max": 0.0001184668595669791,
      "clip_ratio/high_mean": 0.0001184668595669791,
      "clip_ratio/low_mean": 3.080714668612927e-05,
      "clip_ratio/low_min": 3.080714668612927e-05,
      "clip_ratio/region_mean": 0.00014927400625310838,
      "completions/clipped_ratio": 0.0,
      "completions/max_length": 376.6,
      "completions/mean_length": 218.98125,
      "completions/min_length": 116.0,
      "epoch": 0.010725010725010725,
      "frac_reward_zero_std": 0.15,
      "grad_norm": 0.07512736320495605,
      "kl": 0.06674041077494622,
      "learning_rate": 9.632470336074009e-05,
      "loss": -0.019737768173217773,
      "reward": 0.7764474302530289,
      "reward_std": 0.21352720810100437,
      "rewards/GRPOAccuracyReward/mean": 0.7764474302530289,
      "rewards/GRPOAccuracyReward/std": 0.33696491830050945,
      "step": 50
    },
    {
      "clip_ratio/high_max": 0.00028356637340039016,
      "clip_ratio/high_mean": 0.00028356637340039016,
      "clip_ratio/low_mean": 0.0,
      "clip_ratio/low_min": 0.0,
      "clip_ratio/region_mean": 0.00028356637340039016,
      "completions/clipped_ratio": 0.0125,
      "completions/max_length": 392.6,
      "completions/mean_length": 243.8125,
      "completions/min_length": 144.0,
      "epoch": 0.01287001287001287,
      "frac_reward_zero_std": 0.15,
      "grad_norm": 0.10443133860826492,
      "kl": 0.06835343670099973,
      "learning_rate": 9.397368756032445e-05,
      "loss": -0.007591944187879562,
      "reward": 0.7749797284603119,
      "reward_std": 0.19035318903625012,
      "rewards/GRPOAccuracyReward/mean": 0.7749797284603119,
      "rewards/GRPOAccuracyReward/std": 0.28027212638407945,
      "step": 60
    },
    {
      "clip_ratio/high_max": 0.00013208105228841306,
      "clip_ratio/high_mean": 0.00013208105228841306,
      "clip_ratio/low_mean": 9.900189470499754e-05,
      "clip_ratio/low_min": 9.900189470499754e-05,
      "clip_ratio/region_mean": 0.00023108294699341058,
      "completions/clipped_ratio": 0.01875,
      "completions/max_length": 401.8,
      "completions/mean_length": 248.2625,
      "completions/min_length": 140.1,
      "epoch": 0.015015015015015015,
      "frac_reward_zero_std": 0.05,
      "grad_norm": 0.10150457173585892,
      "kl": 0.0705636341124773,
      "learning_rate": 9.108889076126226e-05,
      "loss": -0.009383304417133332,
      "reward": 0.9021358549594879,
      "reward_std": 0.15377899520099164,
      "rewards/GRPOAccuracyReward/mean": 0.9021358549594879,
      "rewards/GRPOAccuracyReward/std": 0.2050409210845828,
      "step": 70
    },
    {
      "clip_ratio/high_max": 0.0003094193030847237,
      "clip_ratio/high_mean": 0.0003094193030847237,
      "clip_ratio/low_mean": 1.4257199654821307e-05,
      "clip_ratio/low_min": 1.4257199654821307e-05,
      "clip_ratio/region_mean": 0.00032367650273954494,
      "completions/clipped_ratio": 0.2125,
      "completions/max_length": 496.0,
      "completions/mean_length": 331.45625,
      "completions/min_length": 179.0,
      "epoch": 0.01716001716001716,
      "frac_reward_zero_std": 0.1,
      "grad_norm": 0.10268519073724747,
      "kl": 0.0750084737315774,
      "learning_rate": 8.770533048884482e-05,
      "loss": 0.04920143485069275,
      "reward": 0.7289010256528854,
      "reward_std": 0.33627076297998426,
      "rewards/GRPOAccuracyReward/mean": 0.7289010256528854,
      "rewards/GRPOAccuracyReward/std": 0.4154147546738386,
      "step": 80
    },
    {
      "clip_ratio/high_max": 3.973673447035253e-05,
      "clip_ratio/high_mean": 3.973673447035253e-05,
      "clip_ratio/low_mean": 0.0,
      "clip_ratio/low_min": 0.0,
      "clip_ratio/region_mean": 3.973673447035253e-05,
      "completions/clipped_ratio": 0.25,
      "completions/max_length": 512.0,
      "completions/mean_length": 327.9875,
      "completions/min_length": 173.3,
      "epoch": 0.019305019305019305,
      "frac_reward_zero_std": 0.15,
      "grad_norm": 0.26367688179016113,
      "kl": 0.08374276980757714,
      "learning_rate": 8.386407858128706e-05,
      "loss": 0.06016837358474732,
      "reward": 0.5620754957199097,
      "reward_std": 0.3342462420463562,
      "rewards/GRPOAccuracyReward/mean": 0.5620754957199097,
      "rewards/GRPOAccuracyReward/std": 0.43870959579944613,
      "step": 90
    },
    {
      "clip_ratio/high_max": 0.0,
      "clip_ratio/high_mean": 0.0,
      "clip_ratio/low_mean": 0.0,
      "clip_ratio/low_min": 0.0,
      "clip_ratio/region_mean": 0.0,
      "completions/clipped_ratio": 0.56875,
      "completions/max_length": 512.0,
      "completions/mean_length": 390.28125,
      "completions/min_length": 156.6,
      "epoch": 0.02145002145002145,
      "frac_reward_zero_std": 0.6,
      "grad_norm": 0.25766587257385254,
      "kl": 0.970554806292057,
      "learning_rate": 7.961176263324901e-05,
      "loss": 0.05362249612808227,
      "reward": 0.18054784536361695,
      "reward_std": 0.15611685663461686,
      "rewards/GRPOAccuracyReward/mean": 0.18054784536361695,
      "rewards/GRPOAccuracyReward/std": 0.1808907210826874,
      "step": 100
    },
    {
      "clip_ratio/high_max": 3.7147101829759775e-05,
      "clip_ratio/high_mean": 3.7147101829759775e-05,
      "clip_ratio/low_mean": 0.0,
      "clip_ratio/low_min": 0.0,
      "clip_ratio/region_mean": 3.7147101829759775e-05,
      "completions/clipped_ratio": 0.4375,
      "completions/max_length": 512.0,
      "completions/mean_length": 350.225,
      "completions/min_length": 117.8,
      "epoch": 0.023595023595023596,
      "frac_reward_zero_std": 0.65,
      "grad_norm": 0.45818907022476196,
      "kl": 1.1629940748214722,
      "learning_rate": 7.500000000000001e-05,
      "loss": 0.06456108689308167,
      "reward": 0.1569143995642662,
      "reward_std": 0.16661429554224014,
      "rewards/GRPOAccuracyReward/mean": 0.1569143995642662,
      "rewards/GRPOAccuracyReward/std": 0.2591667205095291,
      "step": 110
    },
    {
      "clip_ratio/high_max": 7.7220075763762e-05,
      "clip_ratio/high_mean": 7.7220075763762e-05,
      "clip_ratio/low_mean": 1.6103059169836343e-05,
      "clip_ratio/low_min": 1.6103059169836343e-05,
      "clip_ratio/region_mean": 9.332313493359834e-05,
      "completions/clipped_ratio": 0.4,
      "completions/max_length": 512.0,
      "completions/mean_length": 327.9,
      "completions/min_length": 118.9,
      "epoch": 0.02574002574002574,
      "frac_reward_zero_std": 0.2,
      "grad_norm": 0.7808628082275391,
      "kl": 2.8313242219388486,
      "learning_rate": 7.008477123264848e-05,
      "loss": 0.1667671322822571,
      "reward": 0.31317294016480446,
      "reward_std": 0.36595899164676665,
      "rewards/GRPOAccuracyReward/mean": 0.31317294016480446,
      "rewards/GRPOAccuracyReward/std": 0.4505728304386139,
      "step": 120
    },
    {
      "clip_ratio/high_max": 1.87265919521451e-05,
      "clip_ratio/high_mean": 1.87265919521451e-05,
      "clip_ratio/low_mean": 8.211454405682161e-05,
      "clip_ratio/low_min": 8.211454405682161e-05,
      "clip_ratio/region_mean": 0.00010084113600896671,
      "completions/clipped_ratio": 0.4875,
      "completions/max_length": 512.0,
      "completions/mean_length": 335.325,
      "completions/min_length": 124.8,
      "epoch": 0.027885027885027884,
      "frac_reward_zero_std": 0.3,
      "grad_norm": 0.455464631319046,
      "kl": 3.9928509570658206,
      "learning_rate": 6.492574055008473e-05,
      "loss": 0.1944751262664795,
      "reward": 0.33235934376716614,
      "reward_std": 0.2807466521859169,
      "rewards/GRPOAccuracyReward/mean": 0.33235934376716614,
      "rewards/GRPOAccuracyReward/std": 0.4165674805641174,
      "step": 130
    },
    {
      "clip_ratio/high_max": 6.056934944353998e-05,
      "clip_ratio/high_mean": 6.056934944353998e-05,
      "clip_ratio/low_mean": 0.0002872463868698105,
      "clip_ratio/low_min": 0.0002872463868698105,
      "clip_ratio/region_mean": 0.0003478157363133505,
      "completions/clipped_ratio": 0.43125,
      "completions/max_length": 512.0,
      "completions/mean_length": 326.66875,
      "completions/min_length": 112.7,
      "epoch": 0.03003003003003003,
      "frac_reward_zero_std": 0.2,
      "grad_norm": 2.0021891593933105,
      "kl": 6.139404573664069,
      "learning_rate": 5.958553159618693e-05,
      "loss": 0.26804797649383544,
      "reward": 0.4326256915926933,
      "reward_std": 0.3671162545681,
      "rewards/GRPOAccuracyReward/mean": 0.4326256915926933,
      "rewards/GRPOAccuracyReward/std": 0.45894044637680054,
      "step": 140
    },
    {
      "clip_ratio/high_max": 0.00033254593727178873,
      "clip_ratio/high_mean": 0.00033254593727178873,
      "clip_ratio/low_mean": 0.0004617299826350063,
      "clip_ratio/low_min": 0.0004617299826350063,
      "clip_ratio/region_mean": 0.000794275919906795,
      "completions/clipped_ratio": 0.21875,
      "completions/max_length": 446.7,
      "completions/mean_length": 247.4875,
      "completions/min_length": 119.1,
      "epoch": 0.032175032175032175,
      "frac_reward_zero_std": 0.2,
      "grad_norm": 0.19198712706565857,
      "kl": 5.756336740031839,
      "learning_rate": 5.4128967273616625e-05,
      "loss": 0.2045767068862915,
      "reward": 0.6158808812499046,
      "reward_std": 0.3053660370409489,
      "rewards/GRPOAccuracyReward/mean": 0.6158808812499046,
      "rewards/GRPOAccuracyReward/std": 0.3903721943497658,
      "step": 150
    },
    {
      "clip_ratio/high_max": 0.000521555618615821,
      "clip_ratio/high_mean": 0.000521555618615821,
      "clip_ratio/low_mean": 0.00011648021172732115,
      "clip_ratio/low_min": 0.00011648021172732115,
      "clip_ratio/region_mean": 0.0006380358332535252,
      "completions/clipped_ratio": 0.1875,
      "completions/max_length": 495.9,
      "completions/mean_length": 231.55,
      "completions/min_length": 96.3,
      "epoch": 0.03432003432003432,
      "frac_reward_zero_std": 0.15,
      "grad_norm": 0.7325516939163208,
      "kl": 3.8766106314957143,
      "learning_rate": 4.8622282881591906e-05,
      "loss": 0.20900185108184816,
      "reward": 0.5725153923034668,
      "reward_std": 0.3339070111978799,
      "rewards/GRPOAccuracyReward/mean": 0.5725153923034668,
      "rewards/GRPOAccuracyReward/std": 0.48600139915943147,
      "step": 160
    },
    {
      "clip_ratio/high_max": 0.00036777300701942297,
      "clip_ratio/high_mean": 0.00036777300701942297,
      "clip_ratio/low_mean": 0.0012416675672284327,
      "clip_ratio/low_min": 0.0012416675672284327,
      "clip_ratio/region_mean": 0.00160944059753092,
      "completions/clipped_ratio": 0.20625,
      "completions/max_length": 461.9,
      "completions/mean_length": 238.9,
      "completions/min_length": 101.3,
      "epoch": 0.03646503646503647,
      "frac_reward_zero_std": 0.05,
      "grad_norm": 1.6540167331695557,
      "kl": 5.513966259732842,
      "learning_rate": 4.3132322109079596e-05,
      "loss": 0.21947996616363524,
      "reward": 0.5678531050682067,
      "reward_std": 0.39428034871816636,
      "rewards/GRPOAccuracyReward/mean": 0.5678531050682067,
      "rewards/GRPOAccuracyReward/std": 0.45036178529262544,
      "step": 170
    },
    {
      "clip_ratio/high_max": 0.0003943652234738693,
      "clip_ratio/high_mean": 0.0003943652234738693,
      "clip_ratio/low_mean": 0.0006742777768522501,
      "clip_ratio/low_min": 0.0006742777768522501,
      "clip_ratio/region_mean": 0.0010686429974157362,
      "completions/clipped_ratio": 0.1875,
      "completions/max_length": 446.2,
      "completions/mean_length": 237.91875,
      "completions/min_length": 94.8,
      "epoch": 0.03861003861003861,
      "frac_reward_zero_std": 0.15,
      "grad_norm": 0.9999995231628418,
      "kl": 5.972963699884713,
      "learning_rate": 3.772572564296005e-05,
      "loss": 0.2200754165649414,
      "reward": 0.47174900472164155,
      "reward_std": 0.33926252722740174,
      "rewards/GRPOAccuracyReward/mean": 0.47174900472164155,
      "rewards/GRPOAccuracyReward/std": 0.3934975802898407,
      "step": 180
    },
    {
      "clip_ratio/high_max": 0.0002985262515721843,
      "clip_ratio/high_mean": 0.0002985262515721843,
      "clip_ratio/low_mean": 0.0011260808008955792,
      "clip_ratio/low_min": 0.0011260808008955792,
      "clip_ratio/region_mean": 0.0014246070524677635,
      "completions/clipped_ratio": 0.18125,
      "completions/max_length": 508.5,
      "completions/mean_length": 233.375,
      "completions/min_length": 80.5,
      "epoch": 0.04075504075504076,
      "frac_reward_zero_std": 0.3,
      "grad_norm": 2.0837223529815674,
      "kl": 4.15467327684164,
      "learning_rate": 3.2468122240362284e-05,
      "loss": 0.193391752243042,
      "reward": 0.5048024743795395,
      "reward_std": 0.2907917648553848,
      "rewards/GRPOAccuracyReward/mean": 0.5048024743795395,
      "rewards/GRPOAccuracyReward/std": 0.4036029756069183,
      "step": 190
    },
    {
      "clip_ratio/high_max": 0.00038148521562106905,
      "clip_ratio/high_mean": 0.00038148521562106905,
      "clip_ratio/low_mean": 0.0007543810410425067,
      "clip_ratio/low_min": 0.0007543810410425067,
      "clip_ratio/region_mean": 0.0011358662566635757,
      "completions/clipped_ratio": 0.18125,
      "completions/max_length": 491.5,
      "completions/mean_length": 217.725,
      "completions/min_length": 75.5,
      "epoch": 0.0429000429000429,
      "frac_reward_zero_std": 0.25,
      "grad_norm": 0.5679686665534973,
      "kl": 4.995550830289721,
      "learning_rate": 2.7423332084455544e-05,
      "loss": 0.19014389514923097,
      "reward": 0.4892879366874695,
      "reward_std": 0.31749679893255234,
      "rewards/GRPOAccuracyReward/mean": 0.4892879366874695,
      "rewards/GRPOAccuracyReward/std": 0.4750303983688354,
      "step": 200
    },
    {
      "clip_ratio/high_max": 0.0005820296166348272,
      "clip_ratio/high_mean": 0.0005820296166348272,
      "clip_ratio/low_mean": 0.0006407028180547058,
      "clip_ratio/low_min": 0.0006407028180547058,
      "clip_ratio/region_mean": 0.0012227324346895329,
      "completions/clipped_ratio": 0.175,
      "completions/max_length": 415.4,
      "completions/mean_length": 231.54375,
      "completions/min_length": 90.7,
      "epoch": 0.04504504504504504,
      "frac_reward_zero_std": 0.25,
      "grad_norm": 0.44301143288612366,
      "kl": 5.894885955750942,
      "learning_rate": 2.2652592093878666e-05,
      "loss": 0.16639002561569213,
      "reward": 0.4095374420285225,
      "reward_std": 0.2976005032658577,
      "rewards/GRPOAccuracyReward/mean": 0.4095374420285225,
      "rewards/GRPOAccuracyReward/std": 0.41093329191207884,
      "step": 210
    },
    {
      "clip_ratio/high_max": 0.00042175017297267913,
      "clip_ratio/high_mean": 0.00042175017297267913,
      "clip_ratio/low_mean": 0.001437635504407808,
      "clip_ratio/low_min": 0.001437635504407808,
      "clip_ratio/region_mean": 0.0018593856453662737,
      "completions/clipped_ratio": 0.05,
      "completions/max_length": 396.6,
      "completions/mean_length": 172.43125,
      "completions/min_length": 91.2,
      "epoch": 0.04719004719004719,
      "frac_reward_zero_std": 0.05,
      "grad_norm": 0.29421091079711914,
      "kl": 2.775157513283193,
      "learning_rate": 1.821381258950161e-05,
      "loss": 0.13101720809936523,
      "reward": 0.7113625884056092,
      "reward_std": 0.3570148512721062,
      "rewards/GRPOAccuracyReward/mean": 0.7113625884056092,
      "rewards/GRPOAccuracyReward/std": 0.4512891948223114,
      "step": 220
    },
    {
      "clip_ratio/high_max": 0.0005427190597401931,
      "clip_ratio/high_mean": 0.0005427190597401931,
      "clip_ratio/low_mean": 0.0009504455607384443,
      "clip_ratio/low_min": 0.0009504455607384443,
      "clip_ratio/region_mean": 0.0014931646204786376,
      "completions/clipped_ratio": 0.21875,
      "completions/max_length": 512.0,
      "completions/mean_length": 258.4875,
      "completions/min_length": 101.0,
      "epoch": 0.049335049335049334,
      "frac_reward_zero_std": 0.35,
      "grad_norm": 0.36499232053756714,
      "kl": 7.3756695026531816,
      "learning_rate": 1.4160874341577446e-05,
      "loss": 0.26414506435394286,
      "reward": 0.4353089898824692,
      "reward_std": 0.2749785974621773,
      "rewards/GRPOAccuracyReward/mean": 0.4353089898824692,
      "rewards/GRPOAccuracyReward/std": 0.3985881954431534,
      "step": 230
    },
    {
      "clip_ratio/high_max": 0.0012529249303042888,
      "clip_ratio/high_mean": 0.0012529249303042888,
      "clip_ratio/low_mean": 0.0009511651791399345,
      "clip_ratio/low_min": 0.0009511651791399345,
      "clip_ratio/region_mean": 0.0022040901094442233,
      "completions/clipped_ratio": 0.18125,
      "completions/max_length": 486.3,
      "completions/mean_length": 248.30625,
      "completions/min_length": 104.3,
      "epoch": 0.05148005148005148,
      "frac_reward_zero_std": 0.3,
      "grad_norm": 0.4275699555873871,
      "kl": 7.13997054733336,
      "learning_rate": 1.0542974530180327e-05,
      "loss": 0.20824527740478516,
      "reward": 0.37191061228513717,
      "reward_std": 0.3272858917713165,
      "rewards/GRPOAccuracyReward/mean": 0.37191061228513717,
      "rewards/GRPOAccuracyReward/std": 0.46462770104408263,
      "step": 240
    },
    {
      "clip_ratio/high_max": 0.0005558024626225233,
      "clip_ratio/high_mean": 0.0005558024626225233,
      "clip_ratio/low_mean": 7.949652208480985e-05,
      "clip_ratio/low_min": 7.949652208480985e-05,
      "clip_ratio/region_mean": 0.0006352989847073331,
      "completions/clipped_ratio": 0.09375,
      "completions/max_length": 430.2,
      "completions/mean_length": 200.29375,
      "completions/min_length": 73.5,
      "epoch": 0.053625053625053626,
      "frac_reward_zero_std": 0.3,
      "grad_norm": 2.224740743637085,
      "kl": 3.591916711628437,
      "learning_rate": 7.404029558083653e-06,
      "loss": 0.14056471586227418,
      "reward": 0.4856072306632996,
      "reward_std": 0.26869548072572796,
      "rewards/GRPOAccuracyReward/mean": 0.4856072306632996,
      "rewards/GRPOAccuracyReward/std": 0.37429803907871245,
      "step": 250
    },
    {
      "clip_ratio/high_max": 0.00046831507643219084,
      "clip_ratio/high_mean": 0.00046831507643219084,
      "clip_ratio/low_mean": 0.0018026360776275396,
      "clip_ratio/low_min": 0.0018026360776275396,
      "clip_ratio/region_mean": 0.0022709511715220286,
      "completions/clipped_ratio": 0.09375,
      "completions/max_length": 474.9,
      "completions/mean_length": 193.6375,
      "completions/min_length": 71.9,
      "epoch": 0.05577005577005577,
      "frac_reward_zero_std": 0.15,
      "grad_norm": 1.4172250032424927,
      "kl": 5.182732701860369,
      "learning_rate": 4.782141965121128e-06,
      "loss": 0.19501080513000488,
      "reward": 0.5207433521747589,
      "reward_std": 0.37167102862149476,
      "rewards/GRPOAccuracyReward/mean": 0.5207433521747589,
      "rewards/GRPOAccuracyReward/std": 0.49985893368721007,
      "step": 260
    },
    {
      "clip_ratio/high_max": 9.891765366774053e-05,
      "clip_ratio/high_mean": 9.891765366774053e-05,
      "clip_ratio/low_mean": 0.0009558349382132291,
      "clip_ratio/low_min": 0.0009558349382132291,
      "clip_ratio/region_mean": 0.0010547525918809697,
      "completions/clipped_ratio": 0.1875,
      "completions/max_length": 481.4,
      "completions/mean_length": 233.0875,
      "completions/min_length": 84.4,
      "epoch": 0.05791505791505792,
      "frac_reward_zero_std": 0.4,
      "grad_norm": 2.002272129058838,
      "kl": 4.441968074254691,
      "learning_rate": 2.7091379149682685e-06,
      "loss": 0.13539435863494872,
      "reward": 0.3583903133869171,
      "reward_std": 0.24431048112455755,
      "rewards/GRPOAccuracyReward/mean": 0.3583903133869171,
      "rewards/GRPOAccuracyReward/std": 0.416674280166626,
      "step": 270
    },
    {
      "clip_ratio/high_max": 0.0003207257235771976,
      "clip_ratio/high_mean": 0.0003207257235771976,
      "clip_ratio/low_mean": 0.0009819268132559955,
      "clip_ratio/low_min": 0.0009819268132559955,
      "clip_ratio/region_mean": 0.0013026525499299168,
      "completions/clipped_ratio": 0.0875,
      "completions/max_length": 455.1,
      "completions/mean_length": 211.9125,
      "completions/min_length": 69.8,
      "epoch": 0.06006006006006006,
      "frac_reward_zero_std": 0.3,
      "grad_norm": 0.4216472804546356,
      "kl": 4.473758140578866,
      "learning_rate": 1.210180868628219e-06,
      "loss": 0.12409423589706421,
      "reward": 0.35926790684461596,
      "reward_std": 0.29287493228912354,
      "rewards/GRPOAccuracyReward/mean": 0.35926790684461596,
      "rewards/GRPOAccuracyReward/std": 0.39191124141216277,
      "step": 280
    },
    {
      "clip_ratio/high_max": 0.0005764842106145806,
      "clip_ratio/high_mean": 0.0005764842106145806,
      "clip_ratio/low_mean": 0.0010766518535092473,
      "clip_ratio/low_min": 0.0010766518535092473,
      "clip_ratio/region_mean": 0.001653136064123828,
      "completions/clipped_ratio": 0.075,
      "completions/max_length": 391.3,
      "completions/mean_length": 183.98125,
      "completions/min_length": 88.8,
      "epoch": 0.0622050622050622,
      "frac_reward_zero_std": 0.25,
      "grad_norm": 0.4198935031890869,
      "kl": 2.4005844997242094,
      "learning_rate": 3.034661341025258e-07,
      "loss": 0.09968160390853882,
      "reward": 0.6308276116847992,
      "reward_std": 0.3138733357191086,
      "rewards/GRPOAccuracyReward/mean": 0.6308276116847992,
      "rewards/GRPOAccuracyReward/std": 0.42420098185539246,
      "step": 290
    },
    {
      "clip_ratio/high_max": 0.0006673172203591094,
      "clip_ratio/high_mean": 0.0006673172203591094,
      "clip_ratio/low_mean": 0.0005707790551241487,
      "clip_ratio/low_min": 0.0005707790551241487,
      "clip_ratio/region_mean": 0.0012380962754832581,
      "completions/clipped_ratio": 0.125,
      "completions/max_length": 416.3,
      "completions/mean_length": 209.5,
      "completions/min_length": 88.1,
      "epoch": 0.06435006435006435,
      "frac_reward_zero_std": 0.2,
      "grad_norm": 0.8172051906585693,
      "kl": 3.5869735099375246,
      "learning_rate": 0.0,
      "loss": 0.15942728519439697,
      "reward": 0.4664779186248779,
      "reward_std": 0.37155328691005707,
      "rewards/GRPOAccuracyReward/mean": 0.4664779186248779,
      "rewards/GRPOAccuracyReward/std": 0.4517175734043121,
      "step": 300
    }
  ],
  "logging_steps": 10,
  "max_steps": 300,
  "num_input_tokens_seen": 0,
  "num_train_epochs": 1,
  "save_steps": 100,
  "stateful_callbacks": {
    "TrainerControl": {
      "args": {
        "should_epoch_stop": false,
        "should_evaluate": false,
        "should_log": false,
        "should_save": true,
        "should_training_stop": true
      },
      "attributes": {}
    }
  },
  "total_flos": 0.0,
  "train_batch_size": 8,
  "trial_name": null,
  "trial_params": null
}
